py4html.py
py4html-0.0.4.dist-info/METADATA
py4html-0.0.4.dist-info/WHEEL
py4html-0.0.4.dist-info/licenses/LICENSE.txt
py4html-0.0.4.dist-info/RECORD
