Metadata-Version: 2.4
Name: py4html
Version: 0.0.4
Summary: Use Python for front end web development
Project-URL: Homepage, https://github.com/Rubarion/py4html
Project-URL: Issues, https://github.com/Rubarion/py4html/issues
Author-email: Sreehari P V <sreehari.mras@gmail.com>
License-File: LICENSE.txt
Classifier: License :: OSI Approved :: MIT License
Classifier: Operating System :: OS Independent
Classifier: Programming Language :: Python :: 3
Requires-Python: >=3
